MANIFEST.in
setup.py
django_cms_pagetags.egg-info/PKG-INFO
django_cms_pagetags.egg-info/SOURCES.txt
django_cms_pagetags.egg-info/dependency_links.txt
django_cms_pagetags.egg-info/requires.txt
django_cms_pagetags.egg-info/top_level.txt
pagetags/__init__.py
pagetags/admin.py
pagetags/fields.py
pagetags/models.py
pagetags/urls.py
pagetags/views.py
pagetags/static/pagetags/autocomplete.js
pagetags/templates/pagetags/change_form.html
pagetags/templatetags/__init__.py
pagetags/templatetags/page_tags.py