Metadata-Version: 1.0
Name: django-cms-pagetags
Version: 0.1.6
Summary: Tag fileds for CMS pages. Works with django-tagging or django-tagging-ng.
Home-page: https://github.com/pbs/django-cms-pagetags
Author: Calin Furau
Author-email: calin.furau@gmail.com
License: BSD License
Keywords: django-cms django cms tags
Platform: UNKNOWN
